data_process_utils/11111.py
data_process_utils/__init__.py
data_process_utils/api_cloud_document.py
data_process_utils/feishu_warning.py
data_process_utils/llm_utils.py
data_process_utils/log_utils.py
li_log_utils-1.0.0.dist-info/METADATA
li_log_utils-1.0.0.dist-info/WHEEL
li_log_utils-1.0.0.dist-info/entry_points.txt
li_log_utils-1.0.0.dist-info/top_level.txt
li_log_utils-1.0.0.dist-info/RECORD
