Metadata-Version: 2.2
Name: li_log_utils
Version: 1.0.0
Summary: 用于数据格式转换
Home-page: https://gitlab.chehejia.com/xuyang7/mindgpt_dataloop_common_tools/data_process_utils
Author: lirongxuan
Author-email: 24868371772@qq.com
License: Apache License, Version 2.0
Classifier: Programming Language :: Python :: 3
Classifier: License :: OSI Approved :: MIT License
Classifier: Operating System :: OS Independent
Dynamic: author
Dynamic: author-email
Dynamic: classifier
Dynamic: description
Dynamic: home-page
Dynamic: license
Dynamic: summary
